tk_db_utils/.env.example
tk_db_utils/__init__.py
tk_db_utils/config.example.toml
tk_db_utils/config.py
tk_db_utils/curd.py
tk_db_utils/database.py
tk_db_utils/logger.py
tk_db_utils/models.py
tk_db_utils/schema_validator.py
tk_db_utils/utlis.py
tk_db_utils-0.2.1.dist-info/METADATA
tk_db_utils-0.2.1.dist-info/WHEEL
tk_db_utils-0.2.1.dist-info/licenses/LICENSE
tk_db_utils-0.2.1.dist-info/RECORD
