Metadata-Version: 2.4
Name: tk-db-utils
Version: 0.2.1
Summary: 一个基于 SQLAlchemy 2.0 的高可复用数据库工具库，提供完整的 CRUD 操作、批量数据处理和高级数据库功能。
Project-URL: Homepage, https://github.com/tiankongzhise/tk-db-utils
Project-URL: Repository, https://github.com/tiankongzhise/tk-db-utils
Project-URL: Documentation, https://github.com/tiankongzhise/tk-db-utils#readme
Project-URL: Issues, https://github.com/tiankongzhise/tk-db-utils/issues
Author-email: tiankongzhise <tiankongzhise@163.com>
License:                                  Apache License
License-File: LICENSE
Keywords: crud,database,mysql,orm,postgresql,sqlalchemy,sqlite
Classifier: Development Status :: 4 - Beta
Classifier: Intended Audience :: Developers
Classifier: License :: OSI Approved :: Apache Software License
Classifier: Operating System :: OS Independent
Classifier: Programming Language :: Python :: 3
Classifier: Programming Language :: Python :: 3.9
Classifier: Programming Language :: Python :: 3.10
Classifier: Programming Language :: Python :: 3.11
Classifier: Programming Language :: Python :: 3.12
Classifier: Topic :: Database
Classifier: Topic :: Software Development :: Libraries :: Python Modules
Requires-Python: >=3.11
Requires-Dist: pydantic>=2.11.4
Requires-Dist: pymysql>=1.1.1
Requires-Dist: python-dotenv>=1.1.1
Requires-Dist: sqlalchemy>=2.0.40
Requires-Dist: tk-base-utils>=0.3.4
